webcam_face_capture/__init__.py
webcam_face_capture/main.py
webcam_face_capture-1.0.0.dist-info/METADATA
webcam_face_capture-1.0.0.dist-info/WHEEL
webcam_face_capture-1.0.0.dist-info/entry_points.txt
webcam_face_capture-1.0.0.dist-info/top_level.txt
webcam_face_capture-1.0.0.dist-info/RECORD
