Metadata-Version: 2.1
Name: webcam_face_capture
Version: 1.0.0
Summary: A utility to capture faces from webcam and save them in grayscale
Author: Ranjit
Author-email: ranjitmaity95@gmail.com
Classifier: Programming Language :: Python :: 3
Classifier: License :: OSI Approved :: MIT License
Classifier: Operating System :: OS Independent
Requires-Python: >=3.6
Requires-Dist: opencv-python
